nombres_vers_lettres/__init__.py
nombres_vers_lettres/__main__.py
nombres_vers_lettres/_version.py
nombres_vers_lettres/constants.py
nombres_vers_lettres/make_letters.py
nombres_vers_lettres-1.0.4.dist-info/licenses/LICENSE
nombres_vers_lettres-1.0.4.dist-info/METADATA
nombres_vers_lettres-1.0.4.dist-info/WHEEL
nombres_vers_lettres-1.0.4.dist-info/entry_points.txt
nombres_vers_lettres-1.0.4.dist-info/top_level.txt
nombres_vers_lettres-1.0.4.dist-info/RECORD
