Metadata-Version: 2.4
Name: nombres-vers-lettres
Version: 1.0.4
Summary: A Python package to convert numbers to letters (in French).
Home-page: https://github.com/Vincent-Stragier/nombres_vers_lettres
Author: Vincent Stragier
Author-email: vincent.stragier@outlook.com
Project-URL: Bug Tracker, https://github.com/Vincent-Stragier/nombres_vers_lettres/issues
Classifier: Operating System :: OS Independent
Classifier: Programming Language :: Python :: 3
Requires-Python: <4,>=3.10
License-File: LICENSE
Requires-Dist: setuptools>=65.5.1
Dynamic: license-file
